LICENSE
MANIFEST.in
README.md
requirements.txt
setup.py
pymoviedownloader/__init__.py
pymoviedownloader.egg-info/PKG-INFO
pymoviedownloader.egg-info/SOURCES.txt
pymoviedownloader.egg-info/dependency_links.txt
pymoviedownloader.egg-info/entry_points.txt
pymoviedownloader.egg-info/requires.txt
pymoviedownloader.egg-info/top_level.txt
pymoviedownloader/netnaija/__init__.py
pymoviedownloader/netnaija/downloader.py
pymoviedownloader/utils/__init__.py
pymoviedownloader/utils/common.py
pymoviedownloader/utils/driver.py
pymoviedownloader/utils/logger.py